{
  "noWeapon": [
    {
      "tier": "Legendary",
      "attackDamage": 4.0,
      "attackSpeed": 0.1,
      "upgradeFleshCount": 100,
      "partDropProbability": 1.0,
      "weaponHandType" : "oneHanded"
    },
    {
      "tier": "Unique",
      "attackDamage": 8.0,
      "attackSpeed": 0.5,
      "upgradeFleshCount": 50,
      "partDropProbability": 5.0,
      "weaponHandType" : "oneHanded"
    },
    {
      "tier": "Rare",
      "attackDamage": 3.0,
      "attackSpeed": 0.9,
      "upgradeFleshCount": 25,
      "partDropProbability": 30.0,
      "weaponHandType" : "oneHanded"
    },
    {
      "tier": "Common",
      "attackDamage": 2.0,
      "attackSpeed": 0.9,
      "upgradeFleshCount": 10,
      "partDropProbability": 60.0,
      "weaponHandType" : "oneHanded"
    }
  ],
  "shortSword": [
    {
      "tier": "Legendary",
      "attackDamage": 3.0,
      "attackSpeed": 0.1,
      "attackType": "doubleAttack",
      "upgradeFleshCount": 120,
      "partDropProbability": 1.0,
      "weaponHandType" : "oneHanded"
    },
    {
      "tier": "Unique",
      "attackDamage": 1.0,
      "attackSpeed": 0.1,
      "attackType": "doubleAttack",
      "upgradeFleshCount": 60.0,
      "partDropProbability": 4.17,
      "weaponHandType" : "oneHanded"
    },
    {
      "tier": "Rare",
      "attackDamage": 1.0,
      "attackSpeed": 0.1,
      "attackType": "singleAttack",
      "upgradeFleshCount": 30.0,
      "partDropProbability": 25.0,
      "weaponHandType" : "oneHanded"
    },
    {
      "tier": "Common",
      "attackDamage": 1.0,
      "attackSpeed": 0.3,
      "attackType": "singleAttack",
      "upgradeFleshCount": 12,
      "partDropProbability": 50.0,
      "weaponHandType" : "oneHanded"
    }
  ],
  "longSword": [
    {
      "tier": "Legendary",
      "attackDamage": 6.0,
      "attackSpeed": 0.7,
      "attackType": "doubleAttack",
      "upgradeFleshCount": 140,
      "partDropProbability": 1.0,
      "weaponHandType" : "twoHanded"
    },
    {
      "tier": "Unique",
      "attackDamage": 6.0,
      "attackSpeed": 1.1,
      "attackType": "singleAttack",
      "upgradeFleshCount": 70,
      "partDropProbability": 3.57,
      "weaponHandType" : "twoHanded"
    },
    {
      "tier": "Rare",
      "attackDamage": 5.0,
      "attackSpeed": 1.1,
      "attackType": "singleAttack",
      "upgradeFleshCount": 35,
      "partDropProbability": 21.43,
      "weaponHandType" : "twoHanded"
    },
    {
      "tier": "Common",
      "attackDamage": 4.0,
      "attackSpeed": 1.1,
      "attackType": "singleAttack",
      "upgradeFleshCount": 14,
      "partDropProbability": 42.86,
      "weaponHandType" : "twoHanded"
    }
  ],
  "bow": [
    {
      "tier": "Legendary",
      "attackDamage": 15.0,
      "attackSpeed": 0.5,
      "bulletSpeed": 0.1,
      "upgradeFleshCount": 160,
      "partDropProbability": 1.0,
      "weaponHandType" : "twoHanded"
    },
    {
      "tier": "Unique",
      "attackDamage": 15.0,
      "attackSpeed": 1,
      "bulletSpeed": 0.1,
      "upgradeFleshCount": 80,
      "partDropProbability": 3.12,
      "weaponHandType" : "twoHanded"
    },
    {
      "tier": "Rare",
      "attackDamage": 10.0,
      "attackSpeed": 1.25,
      "bulletSpeed": 0.1,
      "upgradeFleshCount": 40,
      "partDropProbability": 18.75,
      "weaponHandType" : "twoHanded"
    },
    {
      "tier": "Common",
      "attackDamage": 10.0,
      "attackSpeed": 1.5,
      "bulletSpeed": 0.2,
      "upgradeFleshCount": 16,
      "partDropProbability": 37.5,
      "weaponHandType" : "twoHanded"
    }
  ],
  "pistol": [
    {
      "tier": "Legendary",
      "attackDamage": 22.0,
      "attackSpeed": 1,
      "bulletSpeed": 0.1,
      "reloadSpeed": 0.5,
      "attackType": "doubleAttack",
      "upgradeFleshCount": 180,
      "partDropProbability": 1.0,
      "weaponHandType" : "oneHanded"
    },
    {
      "tier": "Unique",
      "attackDamage": 20.0,
      "attackSpeed": 1,
      "bulletSpeed": 0.1,
      "reloadSpeed": 0.5,
      "attackType": "doubleAttack",
      "upgradeFleshCount": 90,
      "partDropProbability": 2.78,
      "weaponHandType" : "oneHanded"
    },
    {
      "tier": "Rare",
      "attackDamage": 20.0,
      "attackSpeed": 1.5,
      "bulletSpeed": 0.1,
      "attackType": "doubleAttack",
      "reloadSpeed": 0.5,
      "upgradeFleshCount": 45,
      "partDropProbability": 16.67,
      "weaponHandType" : "oneHanded"
    },
    {
      "tier": "Common",
      "attackDamage": 20.0,
      "attackSpeed": 1.5,
      "bulletSpeed": 0.1,
      "reloadSpeed": 0.5,
      "attackType": "singleAttack",
      "upgradeFleshCount": 18,
      "partDropProbability": 33.33,
      "weaponHandType" : "oneHanded"
    }
  ],
  "rifle": [
    {
      "tier": "Legendary",
      "attackDamage": 22.0,
      "attackSpeed": 1.0,
      "reloadSpeed": 0.0,
      "bulletSpeed": 0.1,
      "maxBulletCount": 999999999,
      "upgradeFleshCount": 200,
      "partDropProbability": 1.0,
      "weaponHandType" : "twoHanded"
    },
    {
      "tier": "Unique",
      "attackDamage": 30.0,
      "attackSpeed": 1.0,
      "bulletSpeed": 0.5,
      "reloadSpeed": 0.8,
      "maxBulletCount": 50,
      "upgradeFleshCount": 100,
      "partDropProbability": 2.5,
      "weaponHandType" : "twoHanded"
    },
    {
      "tier": "Rare",
      "attackDamage": 20.0,
      "attackSpeed": 0.5,
      "bulletSpeed": 0.1,
      "reloadSpeed": 1.0,
      "maxBulletCount": 50,
      "upgradeFleshCount": 50,
      "partDropProbability": 15.0,
      "weaponHandType" : "twoHanded"
    },
    {
      "tier": "Common",
      "attackDamage": 25.0,
      "attackSpeed": 0.5,
      "bulletSpeed": 0.1,
      "reloadSpeed": 1.1,
      "maxBulletCount": 30,
      "upgradeFleshCount": 20,
      "partDropProbability": 30.0,
      "weaponHandType" : "twoHanded"
    }
  ]
}